eqa/__init__.py
eqa/const/__init__.py
eqa/const/config_ability.py
eqa/const/config_char.py
eqa/const/config_chat_npc.py
eqa/const/config_chat_received.py
eqa/const/config_chat_sent.py
eqa/const/config_combat.py
eqa/const/config_command.py
eqa/const/config_emote.py
eqa/const/config_group.py
eqa/const/config_loot.py
eqa/const/config_other.py
eqa/const/config_pets.py
eqa/const/config_settings.py
eqa/const/config_spell_general.py
eqa/const/config_spell_specific.py
eqa/const/config_system.py
eqa/const/config_who.py
eqa/const/config_zones.py
eqa/const/data_spell_casters.py
eqa/const/data_spell_items.py
eqa/const/data_spell_lines.py
eqa/const/validspells.py
eqa/eqalert.py
eqa/lib/__init__.py
eqa/lib/action.py
eqa/lib/config.py
eqa/lib/curses.py
eqa/lib/encounter.py
eqa/lib/keys.py
eqa/lib/log.py
eqa/lib/parser.py
eqa/lib/settings.py
eqa/lib/sound.py
eqa/lib/state.py
eqa/lib/struct.py
eqa/lib/timer.py
eqa/lib/util.py
eqa/lib/watch.py
eqa/models/__init__.py
eqa/models/config.py
eqa/models/data.py
eqa/models/util.py
eqa/sound/__init__.py
eqa/sound/tick.wav
eqa/sound/tock.wav
eqalert-3.7.3.dist-info/LICENSE
eqalert-3.7.3.dist-info/METADATA
eqalert-3.7.3.dist-info/WHEEL
eqalert-3.7.3.dist-info/entry_points.txt
eqalert-3.7.3.dist-info/RECORD
