Metadata-Version: 2.1
Name: eqalert
Version: 3.7.3
Summary: Configurable and Context Driven Project 1999 Log Parser
License: GPL2
Author: M Geitz
Author-email: git@geitz.xyz
Requires-Python: >=3.9.0,<3.12
Classifier: License :: Other/Proprietary License
Classifier: Programming Language :: Python :: 3
Classifier: Programming Language :: Python :: 3.9
Classifier: Programming Language :: Python :: 3.10
Classifier: Programming Language :: Python :: 3.11
Requires-Dist: coqui-tts (>=0.24.1,<0.25.0)
Requires-Dist: gtts (>=2.3.2,<2.4.0)
Requires-Dist: playsound (>=1.3.0,<1.4.0)
Requires-Dist: pytest-cov (>=5.0.0,<6.0.0)
